{
    "title": "Monster Manual",
    "urlName": "rules/mm",
    "anchorName": "",
    "subsections": [
        {
            "title": "A | Monsters",
            "urlName": "rules/mm/monsters-a",
            "anchorName": "#AMonsters",
            "subsections": [
                {
                    "title": "Aarakocra",
                    "urlName": "rules/mm/monsters-a",
                    "anchorName": "#Aarakocra",
                    "subsections": []
                },
                {
                    "title": "Aboleth",
                    "urlName": "rules/mm/monsters-a",
                    "anchorName": "#Aboleth",
                    "subsections": [
                        {
                            "title": "An Aboleth’s Lair",
                            "urlName": "rules/mm/monsters-a",
                            "anchorName": "#AnAbolethsLair",
                            "subsections": [
                                {
                                    "title": "Lair Actions",
                                    "urlName": "rules/mm/monsters-a",
                                    "anchorName": "#LairActions",
                                    "subsections": []
                                },
                                {
                                    "title": "Regional Effects",
                                    "urlName": "rules/mm/monsters-a",
                                    "anchorName": "#RegionalEffects",
                                    "subsections": []
                                }
                            ]
                        }
                    ]
                },
                {
                    "title": "Angels",
                    "urlName": "rules/mm/monsters-a",
                    "anchorName": "#Angels",
                    "subsections": [
                        {
                            "title": "Deva",
                            "urlName": "rules/mm/monsters-a",
                            "anchorName": "#Deva",
                            "subsections": []
                        },
                        {
                            "title": "Planetar",
                            "urlName": "rules/mm/monsters-a",
                            "anchorName": "#Planetar",
                            "subsections": []
                        },
                        {
                            "title": "Solar",
                            "urlName": "rules/mm/monsters-a",
                            "anchorName": "#Solar",
                            "subsections": []
                        }
                    ]
                },
                {
                    "title": "Animated Objects",
                    "urlName": "rules/mm/monsters-a",
                    "anchorName": "#AnimatedObjects",
                    "subsections": [
                        {
                            "title": "Animated Armor",
                            "urlName": "rules/mm/monsters-a",
                            "anchorName": "#AnimatedArmor",
                            "subsections": []
                        },
                        {
                            "title": "Flying Sword",
                            "urlName": "rules/mm/monsters-a",
                            "anchorName": "#FlyingSword",
                            "subsections": []
                        },
                        {
                            "title": "Rug of Smothering",
                            "urlName": "rules/mm/monsters-a",
                            "anchorName": "#RugofSmothering",
                            "subsections": []
                        }
                    ]
                },
                {
                    "title": "Ankheg",
                    "urlName": "rules/mm/monsters-a",
                    "anchorName": "#Ankheg",
                    "subsections": []
                },
                {
                    "title": "Azer",
                    "urlName": "rules/mm/monsters-a",
                    "anchorName": "#Azer",
                    "subsections": []
                }
            ]
        },
        {
            "title": "B | Monsters",
            "urlName": "rules/mm/monsters-b",
            "anchorName": "#BMonsters",
            "subsections": [
                {
                    "title": "Banshee",
                    "urlName": "rules/mm/monsters-b",
                    "anchorName": "#Banshee",
                    "subsections": []
                },
                {
                    "title": "Basilisk",
                    "urlName": "rules/mm/monsters-b",
                    "anchorName": "#Basilisk",
                    "subsections": []
                },
                {
                    "title": "Behir",
                    "urlName": "rules/mm/monsters-b",
                    "anchorName": "#Behir",
                    "subsections": []
                },
                {
                    "title": "Beholders",
                    "urlName": "rules/mm/monsters-b",
                    "anchorName": "#Beholders",
                    "subsections": [
                        {
                            "title": "A Beholder’s Lair",
                            "urlName": "rules/mm/monsters-b",
                            "anchorName": "#ABeholdersLair",
                            "subsections": [
                                {
                                    "title": "Lair Actions",
                                    "urlName": "rules/mm/monsters-b",
                                    "anchorName": "#LairActions",
                                    "subsections": []
                                },
                                {
                                    "title": "Regional Effects",
                                    "urlName": "rules/mm/monsters-b",
                                    "anchorName": "#RegionalEffects",
                                    "subsections": []
                                }
                            ]
                        },
                        {
                            "title": "Death Tyrant",
                            "urlName": "rules/mm/monsters-b",
                            "anchorName": "#DeathTyrant",
                            "subsections": []
                        },
                        {
                            "title": "A Death Tyrant’s Lair",
                            "urlName": "rules/mm/monsters-b",
                            "anchorName": "#ADeathTyrantsLair",
                            "subsections": [
                                {
                                    "title": "Lair Actions",
                                    "urlName": "rules/mm/monsters-b",
                                    "anchorName": "#LairActions",
                                    "subsections": []
                                },
                                {
                                    "title": "Regional Effects",
                                    "urlName": "rules/mm/monsters-b",
                                    "anchorName": "#RegionalEffects",
                                    "subsections": []
                                }
                            ]
                        },
                        {
                            "title": "Spectator",
                            "urlName": "rules/mm/monsters-b",
                            "anchorName": "#Spectator",
                            "subsections": []
                        }
                    ]
                },
                {
                    "title": "Blights",
                    "urlName": "rules/mm/monsters-b",
                    "anchorName": "#Blights",
                    "subsections": [
                        {
                            "title": "Needle Blight",
                            "urlName": "rules/mm/monsters-b",
                            "anchorName": "#NeedleBlight",
                            "subsections": []
                        },
                        {
                            "title": "Twig Blight",
                            "urlName": "rules/mm/monsters-b",
                            "anchorName": "#TwigBlight",
                            "subsections": []
                        },
                        {
                            "title": "Vine Blight",
                            "urlName": "rules/mm/monsters-b",
                            "anchorName": "#VineBlight",
                            "subsections": []
                        }
                    ]
                },
                {
                    "title": "Bugbears",
                    "urlName": "rules/mm/monsters-b",
                    "anchorName": "#Bugbears",
                    "subsections": []
                },
                {
                    "title": "Bulette",
                    "urlName": "rules/mm/monsters-b",
                    "anchorName": "#Bulette",
                    "subsections": []
                },
                {
                    "title": "Bullywug",
                    "urlName": "rules/mm/monsters-b",
                    "anchorName": "#Bullywug",
                    "subsections": []
                }
            ]
        },
        {
            "title": "C | Monsters",
            "urlName": "rules/mm/monsters-c",
            "anchorName": "#CMonsters",
            "subsections": [
                {
                    "title": "Cambion",
                    "urlName": "rules/mm/monsters-c",
                    "anchorName": "#Cambion",
                    "subsections": []
                },
                {
                    "title": "Carrion Crawler",
                    "urlName": "rules/mm/monsters-c",
                    "anchorName": "#CarrionCrawler",
                    "subsections": []
                },
                {
                    "title": "Centaur",
                    "urlName": "rules/mm/monsters-c",
                    "anchorName": "#Centaur",
                    "subsections": []
                },
                {
                    "title": "Chimera",
                    "urlName": "rules/mm/monsters-c",
                    "anchorName": "#Chimera",
                    "subsections": []
                },
                {
                    "title": "Chuul",
                    "urlName": "rules/mm/monsters-c",
                    "anchorName": "#Chuul",
                    "subsections": []
                },
                {
                    "title": "Cloaker",
                    "urlName": "rules/mm/monsters-c",
                    "anchorName": "#Cloaker",
                    "subsections": []
                },
                {
                    "title": "Cockatrice",
                    "urlName": "rules/mm/monsters-c",
                    "anchorName": "#Cockatrice",
                    "subsections": []
                },
                {
                    "title": "Couatl",
                    "urlName": "rules/mm/monsters-c",
                    "anchorName": "#Couatl",
                    "subsections": []
                },
                {
                    "title": "Crawling Claw",
                    "urlName": "rules/mm/monsters-c",
                    "anchorName": "#CrawlingClaw",
                    "subsections": []
                },
                {
                    "title": "Cyclops",
                    "urlName": "rules/mm/monsters-c",
                    "anchorName": "#Cyclops",
                    "subsections": []
                }
            ]
        },
        {
            "title": "D | Monsters",
            "urlName": "rules/mm/monsters-d",
            "anchorName": "#DMonsters",
            "subsections": [
                {
                    "title": "Darkmantle",
                    "urlName": "rules/mm/monsters-d",
                    "anchorName": "#Darkmantle",
                    "subsections": []
                },
                {
                    "title": "Death Knight",
                    "urlName": "rules/mm/monsters-d",
                    "anchorName": "#DeathKnight",
                    "subsections": []
                },
                {
                    "title": "Demilich",
                    "urlName": "rules/mm/monsters-d",
                    "anchorName": "#Demilich",
                    "subsections": []
                },
                {
                    "title": "Demons",
                    "urlName": "rules/mm/monsters-d",
                    "anchorName": "#Demons",
                    "subsections": []
                },
                {
                    "title": "Devils",
                    "urlName": "rules/mm/monsters-d",
                    "anchorName": "#Devils",
                    "subsections": []
                },
                {
                    "title": "Dinosaurs",
                    "urlName": "rules/mm/monsters-d",
                    "anchorName": "#Dinosaurs",
                    "subsections": []
                },
                {
                    "title": "Displacer Beast",
                    "urlName": "rules/mm/monsters-d",
                    "anchorName": "#DisplacerBeast",
                    "subsections": []
                },
                {
                    "title": "Doppelganger",
                    "urlName": "rules/mm/monsters-d",
                    "anchorName": "#Doppelganger",
                    "subsections": []
                },
                {
                    "title": "Dracolich",
                    "urlName": "rules/mm/monsters-d",
                    "anchorName": "#Dracolich",
                    "subsections": []
                },
                {
                    "title": "Dragon, Shadow",
                    "urlName": "rules/mm/monsters-d",
                    "anchorName": "#DragonShadow",
                    "subsections": []
                },
                {
                    "title": "Dragons",
                    "urlName": "rules/mm/monsters-d",
                    "anchorName": "#Dragons",
                    "subsections": []
                },
                {
                    "title": "Dragon Turtle",
                    "urlName": "rules/mm/monsters-d",
                    "anchorName": "#DragonTurtle",
                    "subsections": []
                },
                {
                    "title": "Drider",
                    "urlName": "rules/mm/monsters-d",
                    "anchorName": "#Drider",
                    "subsections": []
                },
                {
                    "title": "Dryad",
                    "urlName": "rules/mm/monsters-d",
                    "anchorName": "#Dryad",
                    "subsections": []
                },
                {
                    "title": "Duergar",
                    "urlName": "rules/mm/monsters-d",
                    "anchorName": "#Duergar",
                    "subsections": []
                }
            ]
        },
        {
            "title": "E | Monsters",
            "urlName": "rules/mm/monsters-e",
            "anchorName": "#EMonsters",
            "subsections": [
                {
                    "title": "Elementals",
                    "urlName": "rules/mm/monsters-e",
                    "anchorName": "#Elementals",
                    "subsections": [
                        {
                            "title": "Air Elemental",
                            "urlName": "rules/mm/monsters-e",
                            "anchorName": "#AirElemental",
                            "subsections": []
                        },
                        {
                            "title": "Earth Elemental",
                            "urlName": "rules/mm/monsters-e",
                            "anchorName": "#EarthElemental",
                            "subsections": []
                        },
                        {
                            "title": "Fire Elemental",
                            "urlName": "rules/mm/monsters-e",
                            "anchorName": "#FireElemental",
                            "subsections": []
                        },
                        {
                            "title": "Water Elemental",
                            "urlName": "rules/mm/monsters-e",
                            "anchorName": "#WaterElemental",
                            "subsections": []
                        }
                    ]
                },
                {
                    "title": "Elves: Drow",
                    "urlName": "rules/mm/monsters-e",
                    "anchorName": "#ElvesDrow",
                    "subsections": [
                        {
                            "title": "Drow Elite Warrior",
                            "urlName": "rules/mm/monsters-e",
                            "anchorName": "#DrowEliteWarrior",
                            "subsections": []
                        },
                        {
                            "title": "Drow Mage",
                            "urlName": "rules/mm/monsters-e",
                            "anchorName": "#DrowMage",
                            "subsections": []
                        },
                        {
                            "title": "Drow Priestess of Lolth",
                            "urlName": "rules/mm/monsters-e",
                            "anchorName": "#DrowPriestessofLolth",
                            "subsections": []
                        }
                    ]
                },
                {
                    "title": "Empyrean",
                    "urlName": "rules/mm/monsters-e",
                    "anchorName": "#Empyrean",
                    "subsections": []
                },
                {
                    "title": "Ettercap",
                    "urlName": "rules/mm/monsters-e",
                    "anchorName": "#Ettercap",
                    "subsections": []
                },
                {
                    "title": "Ettin",
                    "urlName": "rules/mm/monsters-e",
                    "anchorName": "#Ettin",
                    "subsections": []
                }
            ]
        },
        {
            "title": "F | Monsters",
            "urlName": "rules/mm/monsters-f",
            "anchorName": "#FMonsters",
            "subsections": [
                {
                    "title": "Faerie Dragon",
                    "urlName": "rules/mm/monsters-f",
                    "anchorName": "#FaerieDragon",
                    "subsections": []
                },
                {
                    "title": "Flameskull",
                    "urlName": "rules/mm/monsters-f",
                    "anchorName": "#Flameskull",
                    "subsections": []
                },
                {
                    "title": "Flumph",
                    "urlName": "rules/mm/monsters-f",
                    "anchorName": "#Flumph",
                    "subsections": []
                },
                {
                    "title": "Fomorian",
                    "urlName": "rules/mm/monsters-f",
                    "anchorName": "#Fomorian",
                    "subsections": []
                },
                {
                    "title": "Fungi",
                    "urlName": "rules/mm/monsters-f",
                    "anchorName": "#Fungi",
                    "subsections": [
                        {
                            "title": "Gas Spore",
                            "urlName": "rules/mm/monsters-f",
                            "anchorName": "#GasSpore",
                            "subsections": []
                        },
                        {
                            "title": "Shrieker",
                            "urlName": "rules/mm/monsters-f",
                            "anchorName": "#Shrieker",
                            "subsections": []
                        },
                        {
                            "title": "Violet Fungus",
                            "urlName": "rules/mm/monsters-f",
                            "anchorName": "#VioletFungus",
                            "subsections": []
                        }
                    ]
                }
            ]
        },
        {
            "title": "G | Monsters",
            "urlName": "rules/mm/monsters-g",
            "anchorName": "#GMonsters",
            "subsections": [
                {
                    "title": "Galeb Duhr",
                    "urlName": "rules/mm/monsters-g",
                    "anchorName": "#GalebDuhr",
                    "subsections": []
                },
                {
                    "title": "Gargoyle",
                    "urlName": "rules/mm/monsters-g",
                    "anchorName": "#Gargoyle",
                    "subsections": []
                },
                {
                    "title": "Genies",
                    "urlName": "rules/mm/monsters-g",
                    "anchorName": "#Genies",
                    "subsections": []
                },
                {
                    "title": "Ghost",
                    "urlName": "rules/mm/monsters-g",
                    "anchorName": "#Ghost",
                    "subsections": []
                },
                {
                    "title": "Ghouls",
                    "urlName": "rules/mm/monsters-g",
                    "anchorName": "#Ghouls",
                    "subsections": []
                },
                {
                    "title": "Giants",
                    "urlName": "rules/mm/monsters-g",
                    "anchorName": "#Giants",
                    "subsections": []
                },
                {
                    "title": "Gibbering Mouther",
                    "urlName": "rules/mm/monsters-g",
                    "anchorName": "#GibberingMouther",
                    "subsections": []
                },
                {
                    "title": "Gith",
                    "urlName": "rules/mm/monsters-g",
                    "anchorName": "#Gith",
                    "subsections": []
                },
                {
                    "title": "Gnolls",
                    "urlName": "rules/mm/monsters-g",
                    "anchorName": "#Gnolls",
                    "subsections": []
                },
                {
                    "title": "Deep Gnome (Svirfneblin)",
                    "urlName": "rules/mm/monsters-g",
                    "anchorName": "#DeepGnomeSvirfneblin",
                    "subsections": []
                },
                {
                    "title": "Goblins",
                    "urlName": "rules/mm/monsters-g",
                    "anchorName": "#Goblins",
                    "subsections": []
                },
                {
                    "title": "Golems",
                    "urlName": "rules/mm/monsters-g",
                    "anchorName": "#Golems",
                    "subsections": []
                },
                {
                    "title": "Gorgon",
                    "urlName": "rules/mm/monsters-g",
                    "anchorName": "#Gorgon",
                    "subsections": []
                },
                {
                    "title": "Grell",
                    "urlName": "rules/mm/monsters-g",
                    "anchorName": "#Grell",
                    "subsections": []
                },
                {
                    "title": "Grick",
                    "urlName": "rules/mm/monsters-g",
                    "anchorName": "#Grick",
                    "subsections": []
                },
                {
                    "title": "Griffon",
                    "urlName": "rules/mm/monsters-g",
                    "anchorName": "#Griffon",
                    "subsections": []
                },
                {
                    "title": "Grimlock",
                    "urlName": "rules/mm/monsters-g",
                    "anchorName": "#Grimlock",
                    "subsections": []
                }
            ]
        },
        {
            "title": "H | Monsters",
            "urlName": "rules/mm/monsters-h",
            "anchorName": "#HMonsters",
            "subsections": [
                {
                    "title": "Hags",
                    "urlName": "rules/mm/monsters-h",
                    "anchorName": "#Hags",
                    "subsections": [
                        {
                            "title": "Green Hag",
                            "urlName": "rules/mm/monsters-h",
                            "anchorName": "#GreenHag",
                            "subsections": []
                        },
                        {
                            "title": "Night Hag",
                            "urlName": "rules/mm/monsters-h",
                            "anchorName": "#NightHag",
                            "subsections": []
                        },
                        {
                            "title": "Sea Hag",
                            "urlName": "rules/mm/monsters-h",
                            "anchorName": "#SeaHag",
                            "subsections": []
                        }
                    ]
                },
                {
                    "title": "Half-Dragon",
                    "urlName": "rules/mm/monsters-h",
                    "anchorName": "#HalfDragon",
                    "subsections": [
                        {
                            "title": "Half-Dragon Template",
                            "urlName": "rules/mm/monsters-h",
                            "anchorName": "#HalfDragonTemplate",
                            "subsections": [
                                {
                                    "title": "Sample Half-Dragon",
                                    "urlName": "rules/mm/monsters-h",
                                    "anchorName": "#SampleHalfDragon",
                                    "subsections": []
                                }
                            ]
                        }
                    ]
                },
                {
                    "title": "Harpy",
                    "urlName": "rules/mm/monsters-h",
                    "anchorName": "#Harpy",
                    "subsections": []
                },
                {
                    "title": "Hell Hound",
                    "urlName": "rules/mm/monsters-h",
                    "anchorName": "#HellHound",
                    "subsections": []
                },
                {
                    "title": "Helmed Horror",
                    "urlName": "rules/mm/monsters-h",
                    "anchorName": "#HelmedHorror",
                    "subsections": []
                },
                {
                    "title": "Hippogriff",
                    "urlName": "rules/mm/monsters-h",
                    "anchorName": "#Hippogriff",
                    "subsections": []
                },
                {
                    "title": "Hobgoblins",
                    "urlName": "rules/mm/monsters-h",
                    "anchorName": "#Hobgoblins",
                    "subsections": []
                },
                {
                    "title": "Homunculus",
                    "urlName": "rules/mm/monsters-h",
                    "anchorName": "#Homunculus",
                    "subsections": []
                },
                {
                    "title": "Hook Horror",
                    "urlName": "rules/mm/monsters-h",
                    "anchorName": "#HookHorror",
                    "subsections": []
                },
                {
                    "title": "Hydra",
                    "urlName": "rules/mm/monsters-h",
                    "anchorName": "#Hydra",
                    "subsections": []
                }
            ]
        },
        {
            "title": "I | Monsters",
            "urlName": "rules/mm/monsters-i",
            "anchorName": "#IMonsters",
            "subsections": [
                {
                    "title": "Intellect Devourer",
                    "urlName": "rules/mm/monsters-i",
                    "anchorName": "#IntellectDevourer",
                    "subsections": []
                },
                {
                    "title": "Invisible Stalker",
                    "urlName": "rules/mm/monsters-i",
                    "anchorName": "#InvisibleStalker",
                    "subsections": []
                }
            ]
        },
        {
            "title": "J | Monsters",
            "urlName": "rules/mm/monsters-j",
            "anchorName": "#JMonsters",
            "subsections": [
                {
                    "title": "Jackalwere",
                    "urlName": "rules/mm/monsters-j",
                    "anchorName": "#Jackalwere",
                    "subsections": []
                }
            ]
        },
        {
            "title": "K | Monsters",
            "urlName": "rules/mm/monsters-k",
            "anchorName": "#KMonsters",
            "subsections": [
                {
                    "title": "Kenku",
                    "urlName": "rules/mm/monsters-k",
                    "anchorName": "#Kenku",
                    "subsections": []
                },
                {
                    "title": "Kobolds",
                    "urlName": "rules/mm/monsters-k",
                    "anchorName": "#Kobolds",
                    "subsections": []
                },
                {
                    "title": "Kraken",
                    "urlName": "rules/mm/monsters-k",
                    "anchorName": "#Kraken",
                    "subsections": [
                        {
                            "title": "A Kraken’s Lair",
                            "urlName": "rules/mm/monsters-k",
                            "anchorName": "#AKrakensLair",
                            "subsections": [
                                {
                                    "title": "Lair Actions",
                                    "urlName": "rules/mm/monsters-k",
                                    "anchorName": "#LairActions",
                                    "subsections": []
                                },
                                {
                                    "title": "Regional Effects",
                                    "urlName": "rules/mm/monsters-k",
                                    "anchorName": "#RegionalEffects",
                                    "subsections": []
                                }
                            ]
                        }
                    ]
                },
                {
                    "title": "Kuo-toa",
                    "urlName": "rules/mm/monsters-k",
                    "anchorName": "#Kuotoa",
                    "subsections": []
                }
            ]
        },
        {
            "title": "L | Monsters",
            "urlName": "rules/mm/monsters-l",
            "anchorName": "#LMonsters",
            "subsections": [
                {
                    "title": "Lamia",
                    "urlName": "rules/mm/monsters-l",
                    "anchorName": "#Lamia",
                    "subsections": []
                },
                {
                    "title": "Lich",
                    "urlName": "rules/mm/monsters-l",
                    "anchorName": "#Lich",
                    "subsections": [
                        {
                            "title": "A Lich’s Lair",
                            "urlName": "rules/mm/monsters-l",
                            "anchorName": "#ALichsLair",
                            "subsections": [
                                {
                                    "title": "Lair Actions",
                                    "urlName": "rules/mm/monsters-l",
                                    "anchorName": "#LairActions",
                                    "subsections": []
                                }
                            ]
                        }
                    ]
                },
                {
                    "title": "Lizardfolk",
                    "urlName": "rules/mm/monsters-l",
                    "anchorName": "#Lizardfolk",
                    "subsections": []
                },
                {
                    "title": "Lycanthropes",
                    "urlName": "rules/mm/monsters-l",
                    "anchorName": "#Lycanthropes",
                    "subsections": [
                        {
                            "title": "Werebear",
                            "urlName": "rules/mm/monsters-l",
                            "anchorName": "#Werebear",
                            "subsections": []
                        },
                        {
                            "title": "Wereboar",
                            "urlName": "rules/mm/monsters-l",
                            "anchorName": "#Wereboar",
                            "subsections": []
                        },
                        {
                            "title": "Wererat",
                            "urlName": "rules/mm/monsters-l",
                            "anchorName": "#Wererat",
                            "subsections": []
                        },
                        {
                            "title": "Weretiger",
                            "urlName": "rules/mm/monsters-l",
                            "anchorName": "#Weretiger",
                            "subsections": []
                        },
                        {
                            "title": "Werewolf",
                            "urlName": "rules/mm/monsters-l",
                            "anchorName": "#Werewolf",
                            "subsections": []
                        }
                    ]
                }
            ]
        },
        {
            "title": "M | Monsters",
            "urlName": "rules/mm/monsters-m",
            "anchorName": "#MMonsters",
            "subsections": [
                {
                    "title": "Magmin",
                    "urlName": "rules/mm/monsters-m",
                    "anchorName": "#Magmin",
                    "subsections": []
                },
                {
                    "title": "Manticore",
                    "urlName": "rules/mm/monsters-m",
                    "anchorName": "#Manticore",
                    "subsections": []
                },
                {
                    "title": "Medusa",
                    "urlName": "rules/mm/monsters-m",
                    "anchorName": "#Medusa",
                    "subsections": []
                },
                {
                    "title": "Mephits",
                    "urlName": "rules/mm/monsters-m",
                    "anchorName": "#Mephits",
                    "subsections": [
                        {
                            "title": "Dust Mephit",
                            "urlName": "rules/mm/monsters-m",
                            "anchorName": "#DustMephit",
                            "subsections": []
                        },
                        {
                            "title": "Ice Mephit",
                            "urlName": "rules/mm/monsters-m",
                            "anchorName": "#IceMephit",
                            "subsections": []
                        },
                        {
                            "title": "Magma Mephit",
                            "urlName": "rules/mm/monsters-m",
                            "anchorName": "#MagmaMephit",
                            "subsections": []
                        },
                        {
                            "title": "Mud Mephit",
                            "urlName": "rules/mm/monsters-m",
                            "anchorName": "#MudMephit",
                            "subsections": []
                        },
                        {
                            "title": "Smoke Mephit",
                            "urlName": "rules/mm/monsters-m",
                            "anchorName": "#SmokeMephit",
                            "subsections": []
                        },
                        {
                            "title": "Steam Mephit",
                            "urlName": "rules/mm/monsters-m",
                            "anchorName": "#SteamMephit",
                            "subsections": []
                        }
                    ]
                },
                {
                    "title": "Merfolk",
                    "urlName": "rules/mm/monsters-m",
                    "anchorName": "#Merfolk",
                    "subsections": []
                },
                {
                    "title": "Merrow",
                    "urlName": "rules/mm/monsters-m",
                    "anchorName": "#Merrow",
                    "subsections": []
                },
                {
                    "title": "Mimic",
                    "urlName": "rules/mm/monsters-m",
                    "anchorName": "#Mimic",
                    "subsections": []
                },
                {
                    "title": "Mind Flayer",
                    "urlName": "rules/mm/monsters-m",
                    "anchorName": "#MindFlayer",
                    "subsections": []
                },
                {
                    "title": "Minotaur",
                    "urlName": "rules/mm/monsters-m",
                    "anchorName": "#Minotaur",
                    "subsections": []
                },
                {
                    "title": "Modrons",
                    "urlName": "rules/mm/monsters-m",
                    "anchorName": "#Modrons",
                    "subsections": [
                        {
                            "title": "Monodrone",
                            "urlName": "rules/mm/monsters-m",
                            "anchorName": "#Monodrone",
                            "subsections": []
                        },
                        {
                            "title": "Duodrone",
                            "urlName": "rules/mm/monsters-m",
                            "anchorName": "#Duodrone",
                            "subsections": []
                        },
                        {
                            "title": "Tridrone",
                            "urlName": "rules/mm/monsters-m",
                            "anchorName": "#Tridrone",
                            "subsections": []
                        },
                        {
                            "title": "Quadrone",
                            "urlName": "rules/mm/monsters-m",
                            "anchorName": "#Quadrone",
                            "subsections": []
                        },
                        {
                            "title": "Pentadrone",
                            "urlName": "rules/mm/monsters-m",
                            "anchorName": "#Pentadrone",
                            "subsections": []
                        }
                    ]
                },
                {
                    "title": "Mummies",
                    "urlName": "rules/mm/monsters-m",
                    "anchorName": "#Mummies",
                    "subsections": [
                        {
                            "title": "Mummy Lord",
                            "urlName": "rules/mm/monsters-m",
                            "anchorName": "#MummyLord",
                            "subsections": []
                        },
                        {
                            "title": "A Mummy Lord’s Lair",
                            "urlName": "rules/mm/monsters-m",
                            "anchorName": "#AMummyLordsLair",
                            "subsections": [
                                {
                                    "title": "Lair Actions",
                                    "urlName": "rules/mm/monsters-m",
                                    "anchorName": "#LairActions",
                                    "subsections": []
                                },
                                {
                                    "title": "Regional Effects",
                                    "urlName": "rules/mm/monsters-m",
                                    "anchorName": "#RegionalEffects",
                                    "subsections": []
                                }
                            ]
                        }
                    ]
                },
                {
                    "title": "Myconids",
                    "urlName": "rules/mm/monsters-m",
                    "anchorName": "#Myconids",
                    "subsections": [
                        {
                            "title": "Spore Servant Template",
                            "urlName": "rules/mm/monsters-m",
                            "anchorName": "#SporeServantTemplate",
                            "subsections": [
                                {
                                    "title": "Sample Spore Servant",
                                    "urlName": "rules/mm/monsters-m",
                                    "anchorName": "#SampleSporeServant",
                                    "subsections": []
                                }
                            ]
                        }
                    ]
                }
            ]
        },
        {
            "title": "N | Monsters",
            "urlName": "rules/mm/monsters-n",
            "anchorName": "#NMonsters",
            "subsections": [
                {
                    "title": "Nagas",
                    "urlName": "rules/mm/monsters-n",
                    "anchorName": "#Nagas",
                    "subsections": [
                        {
                            "title": "Bone Naga",
                            "urlName": "rules/mm/monsters-n",
                            "anchorName": "#BoneNaga",
                            "subsections": []
                        },
                        {
                            "title": "Guardian Naga",
                            "urlName": "rules/mm/monsters-n",
                            "anchorName": "#GuardianNaga",
                            "subsections": []
                        },
                        {
                            "title": "Spirit Naga",
                            "urlName": "rules/mm/monsters-n",
                            "anchorName": "#SpiritNaga",
                            "subsections": []
                        }
                    ]
                },
                {
                    "title": "Nightmare",
                    "urlName": "rules/mm/monsters-n",
                    "anchorName": "#Nightmare",
                    "subsections": []
                },
                {
                    "title": "Nothic",
                    "urlName": "rules/mm/monsters-n",
                    "anchorName": "#Nothic",
                    "subsections": []
                }
            ]
        },
        {
            "title": "O | Monsters",
            "urlName": "rules/mm/monsters-o",
            "anchorName": "#OMonsters",
            "subsections": [
                {
                    "title": "Ogres",
                    "urlName": "rules/mm/monsters-o",
                    "anchorName": "#Ogres",
                    "subsections": []
                },
                {
                    "title": "Oni",
                    "urlName": "rules/mm/monsters-o",
                    "anchorName": "#Oni",
                    "subsections": []
                },
                {
                    "title": "Oozes",
                    "urlName": "rules/mm/monsters-o",
                    "anchorName": "#Oozes",
                    "subsections": []
                },
                {
                    "title": "Orcs",
                    "urlName": "rules/mm/monsters-o",
                    "anchorName": "#Orcs",
                    "subsections": []
                },
                {
                    "title": "Otyugh",
                    "urlName": "rules/mm/monsters-o",
                    "anchorName": "#Otyugh",
                    "subsections": []
                },
                {
                    "title": "Owlbear",
                    "urlName": "rules/mm/monsters-o",
                    "anchorName": "#Owlbear",
                    "subsections": []
                }
            ]
        },
        {
            "title": "P | Monsters",
            "urlName": "rules/mm/monsters-p",
            "anchorName": "#PMonsters",
            "subsections": [
                {
                    "title": "Pegasus",
                    "urlName": "rules/mm/monsters-p",
                    "anchorName": "#Pegasus",
                    "subsections": []
                },
                {
                    "title": "Peryton",
                    "urlName": "rules/mm/monsters-p",
                    "anchorName": "#Peryton",
                    "subsections": []
                },
                {
                    "title": "Piercer",
                    "urlName": "rules/mm/monsters-p",
                    "anchorName": "#Piercer",
                    "subsections": []
                },
                {
                    "title": "Pixie",
                    "urlName": "rules/mm/monsters-p",
                    "anchorName": "#Pixie",
                    "subsections": []
                },
                {
                    "title": "Pseudodragon",
                    "urlName": "rules/mm/monsters-p",
                    "anchorName": "#Pseudodragon",
                    "subsections": []
                },
                {
                    "title": "Purple Worm",
                    "urlName": "rules/mm/monsters-p",
                    "anchorName": "#PurpleWorm",
                    "subsections": []
                }
            ]
        },
        {
            "title": "Q | Monsters",
            "urlName": "rules/mm/monsters-q",
            "anchorName": "#QMonsters",
            "subsections": [
                {
                    "title": "Quaggoth",
                    "urlName": "rules/mm/monsters-q",
                    "anchorName": "#Quaggoth",
                    "subsections": []
                }
            ]
        },
        {
            "title": "R | Monsters",
            "urlName": "rules/mm/monsters-r",
            "anchorName": "#RMonsters",
            "subsections": [
                {
                    "title": "Rakshasa",
                    "urlName": "rules/mm/monsters-r",
                    "anchorName": "#Rakshasa",
                    "subsections": []
                },
                {
                    "title": "Remorhazes",
                    "urlName": "rules/mm/monsters-r",
                    "anchorName": "#Remorhazes",
                    "subsections": []
                },
                {
                    "title": "Revenant",
                    "urlName": "rules/mm/monsters-r",
                    "anchorName": "#Revenant",
                    "subsections": []
                },
                {
                    "title": "Roc",
                    "urlName": "rules/mm/monsters-r",
                    "anchorName": "#Roc",
                    "subsections": []
                },
                {
                    "title": "Roper",
                    "urlName": "rules/mm/monsters-r",
                    "anchorName": "#Roper",
                    "subsections": []
                },
                {
                    "title": "Rust Monster",
                    "urlName": "rules/mm/monsters-r",
                    "anchorName": "#RustMonster",
                    "subsections": []
                }
            ]
        },
        {
            "title": "S | Monsters",
            "urlName": "rules/mm/monsters-s",
            "anchorName": "#SMonsters",
            "subsections": [
                {
                    "title": "Sahuagin",
                    "urlName": "rules/mm/monsters-s",
                    "anchorName": "#Sahuagin",
                    "subsections": []
                },
                {
                    "title": "Salamanders",
                    "urlName": "rules/mm/monsters-s",
                    "anchorName": "#Salamanders",
                    "subsections": []
                },
                {
                    "title": "Satyr",
                    "urlName": "rules/mm/monsters-s",
                    "anchorName": "#Satyr",
                    "subsections": []
                },
                {
                    "title": "Scarecrow",
                    "urlName": "rules/mm/monsters-s",
                    "anchorName": "#Scarecrow",
                    "subsections": []
                },
                {
                    "title": "Shadow",
                    "urlName": "rules/mm/monsters-s",
                    "anchorName": "#Shadow",
                    "subsections": []
                },
                {
                    "title": "Shambling Mound",
                    "urlName": "rules/mm/monsters-s",
                    "anchorName": "#ShamblingMound",
                    "subsections": []
                },
                {
                    "title": "Shield Guardian",
                    "urlName": "rules/mm/monsters-s",
                    "anchorName": "#ShieldGuardian",
                    "subsections": []
                },
                {
                    "title": "Skeletons",
                    "urlName": "rules/mm/monsters-s",
                    "anchorName": "#Skeletons",
                    "subsections": []
                },
                {
                    "title": "Slaadi",
                    "urlName": "rules/mm/monsters-s",
                    "anchorName": "#Slaadi",
                    "subsections": [
                        {
                            "title": "Red Slaad",
                            "urlName": "rules/mm/monsters-s",
                            "anchorName": "#RedSlaad",
                            "subsections": []
                        },
                        {
                            "title": "Blue Slaad",
                            "urlName": "rules/mm/monsters-s",
                            "anchorName": "#BlueSlaad",
                            "subsections": []
                        },
                        {
                            "title": "Green Slaad",
                            "urlName": "rules/mm/monsters-s",
                            "anchorName": "#GreenSlaad",
                            "subsections": []
                        },
                        {
                            "title": "Gray Slaad",
                            "urlName": "rules/mm/monsters-s",
                            "anchorName": "#GraySlaad",
                            "subsections": []
                        },
                        {
                            "title": "Death Slaad",
                            "urlName": "rules/mm/monsters-s",
                            "anchorName": "#DeathSlaad",
                            "subsections": []
                        }
                    ]
                },
                {
                    "title": "Specter",
                    "urlName": "rules/mm/monsters-s",
                    "anchorName": "#Specter",
                    "subsections": []
                },
                {
                    "title": "Sphinxes",
                    "urlName": "rules/mm/monsters-s",
                    "anchorName": "#Sphinxes",
                    "subsections": [
                        {
                            "title": "Androsphinx",
                            "urlName": "rules/mm/monsters-s",
                            "anchorName": "#Androsphinx",
                            "subsections": []
                        },
                        {
                            "title": "Gynosphinx",
                            "urlName": "rules/mm/monsters-s",
                            "anchorName": "#Gynosphinx",
                            "subsections": []
                        },
                        {
                            "title": "A Sphinx’s Lair",
                            "urlName": "rules/mm/monsters-s",
                            "anchorName": "#ASphinxsLair",
                            "subsections": [
                                {
                                    "title": "Lair Actions",
                                    "urlName": "rules/mm/monsters-s",
                                    "anchorName": "#LairActions",
                                    "subsections": []
                                }
                            ]
                        }
                    ]
                },
                {
                    "title": "Sprite",
                    "urlName": "rules/mm/monsters-s",
                    "anchorName": "#Sprite",
                    "subsections": []
                },
                {
                    "title": "Stirge",
                    "urlName": "rules/mm/monsters-s",
                    "anchorName": "#Stirge",
                    "subsections": []
                },
                {
                    "title": "Succubus/Incubus",
                    "urlName": "rules/mm/monsters-s",
                    "anchorName": "#SuccubusIncubus",
                    "subsections": []
                }
            ]
        },
        {
            "title": "T | Monsters",
            "urlName": "rules/mm/monsters-t",
            "anchorName": "#TMonsters",
            "subsections": [
                {
                    "title": "Tarrasque",
                    "urlName": "rules/mm/monsters-t",
                    "anchorName": "#Tarrasque",
                    "subsections": []
                },
                {
                    "title": "Thri-kreen",
                    "urlName": "rules/mm/monsters-t",
                    "anchorName": "#Thrikreen",
                    "subsections": []
                },
                {
                    "title": "Treant",
                    "urlName": "rules/mm/monsters-t",
                    "anchorName": "#Treant",
                    "subsections": []
                },
                {
                    "title": "Troglodyte",
                    "urlName": "rules/mm/monsters-t",
                    "anchorName": "#Troglodyte",
                    "subsections": []
                },
                {
                    "title": "Troll",
                    "urlName": "rules/mm/monsters-t",
                    "anchorName": "#Troll",
                    "subsections": []
                }
            ]
        },
        {
            "title": "U | Monsters",
            "urlName": "rules/mm/monsters-u",
            "anchorName": "#UMonsters",
            "subsections": [
                {
                    "title": "Umber Hulk",
                    "urlName": "rules/mm/monsters-u",
                    "anchorName": "#UmberHulk",
                    "subsections": []
                },
                {
                    "title": "Unicorn",
                    "urlName": "rules/mm/monsters-u",
                    "anchorName": "#Unicorn",
                    "subsections": [
                        {
                            "title": "A Unicorn’s Lair",
                            "urlName": "rules/mm/monsters-u",
                            "anchorName": "#AUnicornsLair",
                            "subsections": [
                                {
                                    "title": "Regional Effects",
                                    "urlName": "rules/mm/monsters-u",
                                    "anchorName": "#RegionalEffects",
                                    "subsections": []
                                }
                            ]
                        }
                    ]
                }
            ]
        },
        {
            "title": "V | Monsters",
            "urlName": "rules/mm/monsters-v",
            "anchorName": "#VMonsters",
            "subsections": [
                {
                    "title": "Vampires",
                    "urlName": "rules/mm/monsters-v",
                    "anchorName": "#Vampires",
                    "subsections": [
                        {
                            "title": "A Vampire’s Lair",
                            "urlName": "rules/mm/monsters-v",
                            "anchorName": "#AVampiresLair",
                            "subsections": [
                                {
                                    "title": "Regional Effects",
                                    "urlName": "rules/mm/monsters-v",
                                    "anchorName": "#RegionalEffects",
                                    "subsections": []
                                }
                            ]
                        }
                    ]
                }
            ]
        },
        {
            "title": "W | Monsters",
            "urlName": "rules/mm/monsters-w",
            "anchorName": "#WMonsters",
            "subsections": [
                {
                    "title": "Water Weird",
                    "urlName": "rules/mm/monsters-w",
                    "anchorName": "#WaterWeird",
                    "subsections": []
                },
                {
                    "title": "Wight",
                    "urlName": "rules/mm/monsters-w",
                    "anchorName": "#Wight",
                    "subsections": []
                },
                {
                    "title": "Will-o’-Wisp",
                    "urlName": "rules/mm/monsters-w",
                    "anchorName": "#WilloWisp",
                    "subsections": []
                },
                {
                    "title": "Wraith",
                    "urlName": "rules/mm/monsters-w",
                    "anchorName": "#Wraith",
                    "subsections": []
                },
                {
                    "title": "Wyvern",
                    "urlName": "rules/mm/monsters-w",
                    "anchorName": "#Wyvern",
                    "subsections": []
                }
            ]
        },
        {
            "title": "X | Monsters",
            "urlName": "rules/mm/monsters-x",
            "anchorName": "#XMonsters",
            "subsections": [
                {
                    "title": "Xorn",
                    "urlName": "rules/mm/monsters-x",
                    "anchorName": "#Xorn",
                    "subsections": []
                }
            ]
        },
        {
            "title": "Y | Monsters",
            "urlName": "rules/mm/monsters-y",
            "anchorName": "#YMonsters",
            "subsections": [
                {
                    "title": "Yeti",
                    "urlName": "rules/mm/monsters-y",
                    "anchorName": "#Yeti",
                    "subsections": []
                },
                {
                    "title": "Yuan-ti",
                    "urlName": "rules/mm/monsters-y",
                    "anchorName": "#Yuanti",
                    "subsections": [
                        {
                            "title": "Yuan-ti Abomination",
                            "urlName": "rules/mm/monsters-y",
                            "anchorName": "#YuantiAbomination",
                            "subsections": []
                        },
                        {
                            "title": "Yuan-ti Malison",
                            "urlName": "rules/mm/monsters-y",
                            "anchorName": "#YuantiMalison",
                            "subsections": []
                        },
                        {
                            "title": "Yuan-ti Pureblood",
                            "urlName": "rules/mm/monsters-y",
                            "anchorName": "#YuantiPureblood",
                            "subsections": []
                        }
                    ]
                },
                {
                    "title": "Yugoloths",
                    "urlName": "rules/mm/monsters-y",
                    "anchorName": "#Yugoloths",
                    "subsections": [
                        {
                            "title": "Arcanaloth",
                            "urlName": "rules/mm/monsters-y",
                            "anchorName": "#Arcanaloth",
                            "subsections": []
                        },
                        {
                            "title": "Mezzoloth",
                            "urlName": "rules/mm/monsters-y",
                            "anchorName": "#Mezzoloth",
                            "subsections": []
                        },
                        {
                            "title": "Nycaloth",
                            "urlName": "rules/mm/monsters-y",
                            "anchorName": "#Nycaloth",
                            "subsections": []
                        },
                        {
                            "title": "Ultroloth",
                            "urlName": "rules/mm/monsters-y",
                            "anchorName": "#Ultroloth",
                            "subsections": []
                        }
                    ]
                }
            ]
        },
        {
            "title": "Z | Monsters",
            "urlName": "rules/mm/monsters-z",
            "anchorName": "#ZMonsters",
            "subsections": [
                {
                    "title": "Zombies",
                    "urlName": "rules/mm/monsters-z",
                    "anchorName": "#Zombies",
                    "subsections": []
                }
            ]
        }
    ]
}